SIGNERTIKTOKT/__init__.py
SIGNERTIKTOKT/signer.py
signertiktokt-0.1.0.dist-info/licenses/LICENSE.yaml
signertiktokt-0.1.0.dist-info/METADATA
signertiktokt-0.1.0.dist-info/WHEEL
signertiktokt-0.1.0.dist-info/top_level.txt
signertiktokt-0.1.0.dist-info/RECORD
