Metadata-Version: 2.4
Name: SIGNERTIKTOKT
Version: 0.1.0
Summary: zalos SIGNER TIKTOK
Author: zalos
Author-email: ssssssssssry@sssssss.com
Requires-Python: >=3.6
License-File: LICENSE.yaml
Requires-Dist: requests
Dynamic: author
Dynamic: author-email
Dynamic: license-file
Dynamic: requires-dist
Dynamic: requires-python
Dynamic: summary
